docker_typer/__init__.py
docker_typer/__main__.py
docker_typer/main.py
docker_typer/settings.py
docker_typer/utils.py
docker_typer-0.1.0.dist-info/LICENSE
docker_typer-0.1.0.dist-info/METADATA
docker_typer-0.1.0.dist-info/WHEEL
docker_typer-0.1.0.dist-info/entry_points.txt
docker_typer-0.1.0.dist-info/RECORD
