Metadata-Version: 2.3
Name: docker-typer
Version: 0.1.0
Summary: 
Author: ttungbmt
Author-email: ttungbmt@gmail.com
Requires-Python: >=3.10,<4.0
Classifier: Programming Language :: Python :: 3
Classifier: Programming Language :: Python :: 3.10
Classifier: Programming Language :: Python :: 3.11
Classifier: Programming Language :: Python :: 3.12
Classifier: Programming Language :: Python :: 3.13
Requires-Dist: environs (>=14.1.1,<15.0.0)
Requires-Dist: pendulum (>=3.0.0,<4.0.0)
Requires-Dist: python-dotenv (>=1.0.1,<2.0.0)
Requires-Dist: typer (>=0.15.2,<0.16.0)
